sdpa_multiprecision-0.2.2.dist-info/LICENSE
sdpa_multiprecision-0.2.2.dist-info/WHEEL
sdpa_multiprecision-0.2.2.dist-info/top_level.txt
sdpa_multiprecision-0.2.2.dist-info/METADATA
sdpa_multiprecision-0.2.2.dist-info/RECORD
sdpa_multiprecision.libs/libgmpxx-25f6cf8d.so.4.4.0
sdpa_multiprecision.libs/libgmp-afec2dd4.so.10.2.0
sdpap/fileio.py
sdpap/symcone.py
sdpap/__init__.py
sdpap/param.py
sdpap/matdata.py
sdpap/sdpap.py
sdpap/sdpaputils.py
sdpap/convert.py
sdpap/sdpacall/__init__.py
sdpap/sdpacall/sdpacall.py
sdpap/sdpacall/sdpa.pypy38-pp73-x86_64-linux-gnu.so
sdpap/fvelim/__init__.py
sdpap/fvelim/fvelimext.pypy38-pp73-x86_64-linux-gnu.so
sdpap/fvelim/fvelim.py
sdpap/spcolo/spcoloext.pypy38-pp73-x86_64-linux-gnu.so
sdpap/spcolo/__init__.py
sdpap/spcolo/spcolo.py
sdpap/spcolo/asputils.py
sdpap/spcolo/clique.py
